setup.cfg
setup.py
ssrf/__init__.py
ssrf/algorithm.py
ssrf/test_algorithm.py
ssrf.egg-info/PKG-INFO
ssrf.egg-info/SOURCES.txt
ssrf.egg-info/dependency_links.txt
ssrf.egg-info/top_level.txt