Metadata-Version: 1.1
Name: ssrf
Version: 0.1.5
Summary: Simple Spaced Repetition Formula
Home-page: https://github.com/AdamDz/ssrf-python
Author: Adam Dziendziel
Author-email: adam.dziendziel@gmail.com
License: Creative Commons Attribution-Share Alike license
Platform: UNKNOWN
Classifier: Development Status :: 4 - Beta
Classifier: Intended Audience :: Developers
Classifier: Operating System :: POSIX
Classifier: Programming Language :: Python
Classifier: Programming Language :: Python :: 2
Classifier: Programming Language :: Python :: 2.7
Classifier: Programming Language :: Python :: 3
Classifier: Programming Language :: Python :: 3.3
Classifier: Topic :: Education
